aiida_hyperqueue/__init__.py
aiida_hyperqueue/scheduler.py
aiida_hyperqueue/cli/__init__.py
aiida_hyperqueue/cli/alloc.py
aiida_hyperqueue/cli/install.py
aiida_hyperqueue/cli/root.py
aiida_hyperqueue/cli/server.py
aiida_hyperqueue/cli/params/__init__.py
aiida_hyperqueue/cli/params/arguments.py
aiida_hyperqueue/cli/params/options.py
aiida_hyperqueue-0.3.0.dist-info/entry_points.txt
aiida_hyperqueue-0.3.0.dist-info/licenses/LICENSE
aiida_hyperqueue-0.3.0.dist-info/WHEEL
aiida_hyperqueue-0.3.0.dist-info/METADATA
aiida_hyperqueue-0.3.0.dist-info/RECORD
