Metadata-Version: 2.4
Name: aiida-hyperqueue
Version: 0.3.0
Summary: AiiDA plugin for the HyperQueue metascheduler
Author: Marnik Bercx, Jusong Yu
Requires-Python: >=3.9
Classifier: Framework :: AiiDA
Classifier: Development Status :: 3 - Alpha
Classifier: License :: OSI Approved :: MIT License
Classifier: Operating System :: POSIX :: Linux
Classifier: Operating System :: MacOS :: MacOS X
Classifier: Natural Language :: English
Classifier: Programming Language :: Python
License-File: LICENSE
Requires-Dist: aiida-core~=2.7
Requires-Dist: sphinx ; extra == "docs"
Requires-Dist: myst-parser ; extra == "docs"
Requires-Dist: sphinx-design ; extra == "docs"
Requires-Dist: sphinx-book-theme ; extra == "docs"
Requires-Dist: sphinxcontrib-details-directive~=0.1.0 ; extra == "docs"
Requires-Dist: pre-commit~=3.5 ; extra == "pre-commit"
Requires-Dist: mypy~=1.10.0 ; extra == "pre-commit"
Requires-Dist: pgtest~=1.3.1 ; extra == "tests"
Requires-Dist: coverage~=7.0 ; extra == "tests"
Requires-Dist: pytest~=7.0 ; extra == "tests"
Requires-Dist: pytest-cov~=4.1 ; extra == "tests"
Project-URL: Source, https://github.com/aiidateam/aiida-hyperqueue
Provides-Extra: docs
Provides-Extra: pre-commit
Provides-Extra: tests
